persistent/__init__.py
persistent/_compat.h
persistent/_compat.py
persistent/_ring.abi3.so
persistent/_ring_build.py
persistent/_timestamp.c
persistent/_timestamp.cpython-310-darwin.so
persistent/cPersistence.c
persistent/cPersistence.cpython-310-darwin.so
persistent/cPersistence.h
persistent/cPickleCache.c
persistent/cPickleCache.cpython-310-darwin.so
persistent/dict.py
persistent/interfaces.py
persistent/list.py
persistent/mapping.py
persistent/persistence.py
persistent/picklecache.py
persistent/ring.c
persistent/ring.h
persistent/ring.py
persistent/timestamp.py
persistent/wref.py
persistent/tests/__init__.py
persistent/tests/attrhooks.py
persistent/tests/cucumbers.py
persistent/tests/test__compat.py
persistent/tests/test_compile_flags.py
persistent/tests/test_docs.py
persistent/tests/test_list.py
persistent/tests/test_mapping.py
persistent/tests/test_persistence.py
persistent/tests/test_picklecache.py
persistent/tests/test_ring.py
persistent/tests/test_timestamp.py
persistent/tests/test_wref.py
persistent/tests/utils.py
persistent-6.5.data/headers/cPersistence.h
persistent-6.5.data/headers/ring.h
persistent-6.5.dist-info/licenses/LICENSE.txt
persistent-6.5.dist-info/METADATA
persistent-6.5.dist-info/WHEEL
persistent-6.5.dist-info/top_level.txt
persistent-6.5.dist-info/RECORD
