Metadata-Version: 2.4
Name: persistent
Version: 6.5
Summary: Translucent persistent objects
Author-email: Zope Foundation and contributors <zope-dev@zope.dev>
Maintainer-email: Plone Foundation and contributors <zope-dev@zope.dev>
License-Expression: ZPL-2.1
Project-URL: Documentation, https://persistent.readthedocs.io
Project-URL: Issues, https://github.com/zopefoundation/persistent/issues
Project-URL: Source, https://github.com/zopefoundation/persistent
Project-URL: Changelog, https://github.com/zopefoundation/persistent/blob/master/CHANGES.rst
Classifier: Development Status :: 6 - Mature
Classifier: Framework :: ZODB
Classifier: Intended Audience :: Developers
Classifier: Operating System :: OS Independent
Classifier: Programming Language :: Python
Classifier: Programming Language :: Python :: 3
Classifier: Programming Language :: Python :: 3 :: Only
Classifier: Programming Language :: Python :: 3.10
Classifier: Programming Language :: Python :: 3.11
Classifier: Programming Language :: Python :: 3.12
Classifier: Programming Language :: Python :: 3.13
Classifier: Programming Language :: Python :: 3.14
Classifier: Programming Language :: Python :: Implementation :: CPython
Classifier: Programming Language :: Python :: Implementation :: PyPy
Classifier: Topic :: Database
Classifier: Topic :: Software Development :: Libraries :: Python Modules
Requires-Python: >=3.10
License-File: LICENSE.txt
Requires-Dist: zope.deferredimport
Requires-Dist: zope.interface
Requires-Dist: cffi; platform_python_implementation == "CPython"
Provides-Extra: docs
Requires-Dist: Sphinx; extra == "docs"
Requires-Dist: repoze.sphinx.autointerface; extra == "docs"
Requires-Dist: furo; extra == "docs"
Provides-Extra: test
Requires-Dist: manuel; extra == "test"
Requires-Dist: zope.testrunner>=6.4; extra == "test"
Dynamic: license-file
